<?xml version="1.0" encoding="UTF-8"?>
<WowzaMediaServerPro>
	<VHost>
		<Name>_defaultVHost_</Name>
		<TimeRunning>20397.098</TimeRunning>
		<ConnectionsLimit>0</ConnectionsLimit>
		<ConnectionsCurrent>3</ConnectionsCurrent>
		<ConnectionsTotal>346</ConnectionsTotal>
		<ConnectionsTotalAccepted>346</ConnectionsTotalAccepted>
		<ConnectionsTotalRejected>0</ConnectionsTotalRejected>
		<Application>
			<Name><![CDATA[niceVodServer]]></Name>
			<Status>loaded</Status>
			<TimeRunning>15903.868</TimeRunning>
			<ConnectionsCurrent>0</ConnectionsCurrent>
			<ConnectionsTotal>128</ConnectionsTotal>
			<ConnectionsTotalAccepted>128</ConnectionsTotalAccepted>
			<ConnectionsTotalRejected>0</ConnectionsTotalRejected>
			<ApplicationInstance>
				<Name><![CDATA[2]]></Name>
				<TimeRunning>15721.119</TimeRunning>
				<ConnectionsCurrent>0</ConnectionsCurrent>
				<ConnectionsTotal>0</ConnectionsTotal>
				<ConnectionsTotalAccepted>0</ConnectionsTotalAccepted>
				<ConnectionsTotalRejected>0</ConnectionsTotalRejected>
				<RTMPConnectionCount>0</RTMPConnectionCount>
				<RTPConnectionCount>0</RTPConnectionCount>
				<CupertinoConnectionCount>0</CupertinoConnectionCount>
				<SmoothConnectionCount>0</SmoothConnectionCount>
				<SanJoseConnectionCount>0</SanJoseConnectionCount>
				<RTMPSessionCount>0</RTMPSessionCount>
				<HTTPSessionCount>0</HTTPSessionCount>
				<RTPSessionCount>0</RTPSessionCount>
			</ApplicationInstance>
			<ApplicationInstance>
				<Name><![CDATA[_definst_]]></Name>
				<TimeRunning>92.883</TimeRunning>
				<ConnectionsCurrent>0</ConnectionsCurrent>
				<ConnectionsTotal>1</ConnectionsTotal>
				<ConnectionsTotalAccepted>1</ConnectionsTotalAccepted>
				<ConnectionsTotalRejected>0</ConnectionsTotalRejected>
				<RTMPConnectionCount>0</RTMPConnectionCount>
				<RTPConnectionCount>0</RTPConnectionCount>
				<CupertinoConnectionCount>0</CupertinoConnectionCount>
				<SmoothConnectionCount>0</SmoothConnectionCount>
				<SanJoseConnectionCount>0</SanJoseConnectionCount>
				<RTMPSessionCount>0</RTMPSessionCount>
				<HTTPSessionCount>0</HTTPSessionCount>
				<RTPSessionCount>0</RTPSessionCount>
			</ApplicationInstance>
		</Application>
		<Application>
			<Name><![CDATA[niceStreamingDrmServer]]></Name>
			<Status>unloaded</Status>
		</Application>
		<Application>
			<Name><![CDATA[vod]]></Name>
			<Status>unloaded</Status>
		</Application>
		<Application>
			<Name><![CDATA[niceLiveServer]]></Name>
			<Status>loaded</Status>
			<TimeRunning>20353.034</TimeRunning>
			<ConnectionsCurrent>3</ConnectionsCurrent>
			<ConnectionsTotal>175</ConnectionsTotal>
			<ConnectionsTotalAccepted>175</ConnectionsTotalAccepted>
			<ConnectionsTotalRejected>0</ConnectionsTotalRejected>
			<ApplicationInstance>
				<Name><![CDATA[_definst_]]></Name>
				<TimeRunning>20352.973</TimeRunning>
				<ConnectionsCurrent>3</ConnectionsCurrent>
				<ConnectionsTotal>175</ConnectionsTotal>
				<ConnectionsTotalAccepted>175</ConnectionsTotalAccepted>
				<ConnectionsTotalRejected>0</ConnectionsTotalRejected>
				<RTMPConnectionCount>2</RTMPConnectionCount>
				<RTPConnectionCount>0</RTPConnectionCount>
				<CupertinoConnectionCount>1</CupertinoConnectionCount>
				<SmoothConnectionCount>0</SmoothConnectionCount>
				<SanJoseConnectionCount>0</SanJoseConnectionCount>
				<RTMPSessionCount>2</RTMPSessionCount>
				<HTTPSessionCount>1</HTTPSessionCount>
				<RTPSessionCount>0</RTPSessionCount>
				<Client>
					<ClientId>2075894738</ClientId>
					<FlashVersion>WIN 12,0,0,41</FlashVersion>
					<IpAddress>80.29.63.163</IpAddress>
					<Referrer><![CDATA[http://www.golstadium.com/jwplayer/jwplayer.flash.swf]]></Referrer>
					<QueryString><![CDATA[]]>
					</QueryString>
					<TimeRunning>5713.722</TimeRunning>
					<DateStarted>Thu, Jan 30 2014 14:22:32 +0100</DateStarted>
					<URI><![CDATA[rtmp://CDN22A-EDGE01.mediapro.es:1935/niceLiveServer/_definst_]]></URI>
					<Protocol>RTMP</Protocol>
					<IsSSL>false</IsSSL>
					<IsEncrypted>false</IsEncrypted>
					<Port>1935</Port>
					<LastValidateTime>4569</LastValidateTime>
					<IoSessionBytesSent>539793916</IoSessionBytesSent>
					<IoSessionBytesReceived>7117</IoSessionBytesReceived>
					<IoSessionLastIo>4569</IoSessionLastIo>
					<IoBytesSent>538224939</IoBytesSent>
					<IoBytesReceived>0</IoBytesReceived>
				</Client>
				<Client>
					<ClientId>792837926</ClientId>
					<FlashVersion>WIN 12,0,0,41</FlashVersion>
					<IpAddress>90.162.191.172</IpAddress>
					<Referrer><![CDATA[http://www.golstadium.com/jwplayer/jwplayer.flash.swf]]></Referrer>
					<QueryString><![CDATA[]]>
					</QueryString>
					<TimeRunning>275.325</TimeRunning>
					<DateStarted>Thu, Jan 30 2014 15:53:10 +0100</DateStarted>
					<URI><![CDATA[rtmp://CDN22A-EDGE01.mediapro.es:1935/niceLiveServer/_definst_]]></URI>
					<Protocol>RTMP</Protocol>
					<IsSSL>false</IsSSL>
					<IsEncrypted>false</IsEncrypted>
					<Port>1935</Port>
					<LastValidateTime>1826</LastValidateTime>
					<IoSessionBytesSent>69521329</IoSessionBytesSent>
					<IoSessionBytesReceived>3955</IoSessionBytesReceived>
					<IoSessionLastIo>60</IoSessionLastIo>
					<IoBytesSent>69334492</IoBytesSent>
					<IoBytesReceived>0</IoBytesReceived>
				</Client>
				<HTTPSession>
					<SessionId>380781803</SessionId>
					<IpAddress>83.44.107.139</IpAddress>
					<Referrer><![CDATA[]]>
					</Referrer>
					<QueryString><![CDATA[wowzasessionid=380781803]]></QueryString>
					<TimeRunning>2287.776</TimeRunning>
					<DateStarted>Thu, Jan 30 2014 15:19:38 +0100</DateStarted>
					<URI><![CDATA[niceLiveServer/_definst_/52ea5fb5/fe36a734f5d8d7c6d68ba66d17a48bc9/golt_live_24h_MB_2000/chunklist.m3u8]]></URI>
					<Protocol>cupertinostreaming</Protocol>
					<SessionType>live</SessionType>
					<Port>1935</Port>
					<IoBytesSent>603005295</IoBytesSent>
					<IoBytesReceived>0</IoBytesReceived>
					<IoLastRequest>112</IoLastRequest>
				</HTTPSession>
			</ApplicationInstance>
		</Application>
		<Application>
			<Name><![CDATA[niceVodDrmServer]]></Name>
			<Status>unloaded</Status>
		</Application>
		<Application>
			<Name><![CDATA[niceStreamingHttpOrigin]]></Name>
			<Status>unloaded</Status>
		</Application>
		<Application>
			<Name><![CDATA[niceStreamingServer]]></Name>
			<Status>unloaded</Status>
		</Application>
		<Application>
			<Name><![CDATA[niceLiveDrmServer]]></Name>
			<Status>unloaded</Status>
		</Application>
	</VHost>
</WowzaMediaServerPro>